qset_tslib/__init__.py
qset_tslib/agg.py
qset_tslib/argmin.py
qset_tslib/basic.py
qset_tslib/cs.py
qset_tslib/cython/__init__.py
qset_tslib/cython/neutralize/__init__.py
qset_tslib/cython/neutralize/cneutralize.cpp
qset_tslib/cython/neutralize/cneutralize.pyx
qset_tslib/cython/neutralize/neutralize.py
qset_tslib/ls.py
qset_tslib/math.py
qset_tslib/models/__init__.py
qset_tslib/models/brinson.py
qset_tslib/models/hhi.py
qset_tslib/models/tsne.py
qset_tslib/noise.py
qset_tslib/quantile.py
qset_tslib/rank.py
qset_tslib/regime.py
qset_tslib/reindex.py
qset_tslib/stats.py
qset_tslib/technical_indicators/__init__.py
qset_tslib/technical_indicators/basic.py
qset_tslib/technical_indicators/momentum.py
qset_tslib/technical_indicators/trend.py
qset_tslib/ts.py
qset_tslib-0.1.1.dist-info/WHEEL
qset_tslib-0.1.1.dist-info/METADATA
qset_tslib-0.1.1.dist-info/RECORD
