Metadata-Version: 2.1
Name: qset-tslib
Version: 0.1.1
Summary: 
Author: Arsenii Kadaner
Author-email: arseniikadaner@gmail.com
Requires-Python: >=3.8,<3.10
Classifier: Programming Language :: Python :: 3
Classifier: Programming Language :: Python :: 3.8
Classifier: Programming Language :: Python :: 3.9
Requires-Dist: numpy (>=1.20.1,<2.0.0)
Requires-Dist: pandas (>=1.2.3,<2.0.0)
Requires-Dist: scikit-learn (>=0.23.1,<0.24.0)
Requires-Dist: scipy (>=1.6.2,<2.0.0)
Requires-Dist: statsmodels (>=0.12.2,<0.13.0)
